{"id": "0afb6c9e-a2bf-4f1b-91a4-67ef56922eeb", "code": "#include <cstdint>\n#include <unordered_map>\n#include <set>\n\ntypedef uint64_t obj_id_t;\n\nclass CacheManager {\nprivate:\n    // GDSF with frequency aging: track frequency and size for each object.\n    struct CacheObject {\n        uint64_t freq;\n        uint64_t size;\n        uint64_t timestamp;\n        std::set<std::tuple<double, uint64_t, obj_id_t>>::iterator pqit;\n    };\n    // Priority queue node: tuple for easy erase and reinsert\n    // (priority, timestamp, obj_id)\n    std::set<std::tuple<double, uint64_t, obj_id_t>> priority_set;\n    std::unordered_map<obj_id_t, CacheObject> cache_map;\n    uint64_t counter = 0;\n    double last_evict_pri = 0.0;\n\n    // Slightly decrease freq on every eviction to \"age\" frequency counts\n    void age_frequencies() {\n        for (auto& kv : cache_map) {\n            if (kv.second.freq > 1) kv.second.freq = (kv.second.freq * 7) / 8 + 1;\n        }\n    }\n\n    double calc_pri(uint64_t freq, uint64_t size) {\n        if (size == 0) return last_evict_pri + freq * 1e6;\n        // Add a small recency bonus so that new inserts have a modest advantage\n        return last_evict_pri + double(freq) * 1e6 / size + 0.01 * counter;\n    }\n\npublic:\n    bool find(obj_id_t obj_id) {\n        auto it = cache_map.find(obj_id);\n        if (it == cache_map.end()) return false;\n        // Erase from set using iterator (O(log N))\n        priority_set.erase(it->second.pqit);\n        it->second.freq += 1;\n        it->second.timestamp = ++counter;\n        double new_pri = calc_pri(it->second.freq, it->second.size);\n        auto pqit = priority_set.insert({new_pri, it->second.timestamp, obj_id}).first;\n        it->second.pqit = pqit;\n        return true;\n    }\n\n    void insert(obj_id_t obj_id, uint64_t obj_size) {\n        auto it = cache_map.find(obj_id);\n        if (it != cache_map.end()) {\n            find(obj_id);\n            return;\n        }\n        uint64_t freq = 1;\n        uint64_t ts = ++counter;\n        double pri = calc_pri(freq, obj_size);\n        auto pqit = priority_set.insert({pri, ts, obj_id}).first;\n        cache_map[obj_id] = {freq, obj_size, ts, pqit};\n    }\n\n    obj_id_t evict() {\n        if (priority_set.empty()) return 0;\n        auto it = priority_set.begin();\n        obj_id_t victim = std::get<2>(*it);\n        last_evict_pri = std::get<0>(*it);\n        priority_set.erase(it);\n        cache_map.erase(victim);\n        // Age all frequencies to prevent stale frequency dominance\n        age_frequencies();\n        // Recompute priorities for all objects after frequency aging\n        for (auto& kv : cache_map) {\n            priority_set.erase(kv.second.pqit);\n            double new_pri = calc_pri(kv.second.freq, kv.second.size);\n            kv.second.pqit = priority_set.insert({new_pri, kv.second.timestamp, kv.first}).first;\n        }\n        return victim;\n    }\n};", "language": "python", "parent_id": "114c7dae-40ee-4a46-8e14-bbc698fd2560", "generation": 2, "timestamp": 1763752617.4833443, "iteration_found": 11, "metrics": {"combined_score": -Infinity}, "complexity": 0.0, "diversity": 0.0, "metadata": {"changes": "Change 1: Replace 72 lines with 80 lines", "parent_metrics": {"combined_score": -Infinity}, "island": 0}, "prompts": null, "artifacts_json": null, "artifact_dir": null, "embedding": null}