{"id": "114c7dae-40ee-4a46-8e14-bbc698fd2560", "code": "#include <cstdint>\n#include <unordered_map>\n#include <set>\n\ntypedef uint64_t obj_id_t;\n\nclass CacheManager {\nprivate:\n    // LFU with size-awareness: track frequency and size for each object.\n    struct CacheObject {\n        uint64_t freq;\n        uint64_t size;\n        uint64_t timestamp;\n    };\n    struct LFUNode {\n        double priority;\n        uint64_t timestamp;\n        obj_id_t id;\n        bool operator<(const LFUNode& o) const {\n            if (priority != o.priority) return priority < o.priority;\n            return timestamp < o.timestamp;\n        }\n    };\n\n    std::unordered_map<obj_id_t, CacheObject> cache_map;\n    std::set<LFUNode> priority_set;\n    uint64_t counter = 0;\n    double last_evict_pri = 0.0;\n\n    double calc_pri(uint64_t freq, uint64_t size) {\n        if (size == 0) return last_evict_pri + freq * 1e6;\n        return last_evict_pri + double(freq) * 1e6 / size;\n    }\n\npublic:\n    bool find(obj_id_t obj_id) {\n        auto it = cache_map.find(obj_id);\n        if (it == cache_map.end()) return false;\n        // Erase from set\n        double old_pri = calc_pri(it->second.freq, it->second.size);\n        LFUNode node{old_pri, it->second.timestamp, obj_id};\n        priority_set.erase(node);\n        it->second.freq += 1;\n        it->second.timestamp = ++counter;\n        double new_pri = calc_pri(it->second.freq, it->second.size);\n        priority_set.insert({new_pri, it->second.timestamp, obj_id});\n        return true;\n    }\n\n    void insert(obj_id_t obj_id, uint64_t obj_size) {\n        auto it = cache_map.find(obj_id);\n        if (it != cache_map.end()) {\n            find(obj_id);\n            return;\n        }\n        uint64_t freq = 1;\n        uint64_t ts = ++counter;\n        double pri = calc_pri(freq, obj_size);\n        cache_map[obj_id] = {freq, obj_size, ts};\n        priority_set.insert({pri, ts, obj_id});\n    }\n\n    obj_id_t evict() {\n        if (priority_set.empty()) return 0;\n        auto it = priority_set.begin();\n        obj_id_t victim = it->id;\n        last_evict_pri = it->priority;\n        priority_set.erase(it);\n        cache_map.erase(victim);\n        return victim;\n    }\n};", "language": "python", "parent_id": "6879d981-83e7-4bcf-b58d-0ab35ff75a3a", "generation": 1, "timestamp": 1763752546.2341788, "iteration_found": 4, "metrics": {"combined_score": -Infinity}, "complexity": 0.0, "diversity": 0.0, "metadata": {"changes": "Change 1: Replace 37 lines with 72 lines", "parent_metrics": {"combined_score": 0.8077, "miss_ratio_4": 0.4257, "miss_ratio_45": 0.2907, "miss_ratio_450": 0.1923}, "island": 0}, "prompts": null, "artifacts_json": null, "artifact_dir": null, "embedding": null}